{"1697347":{"level":4,"parents":[{"id":51701,"delta":-2}],"name":"Юра","wikipedia":"en:Canton_of_Jura","index":0,"square":1801500432.44479,"property":{"openStreetMapId":1697347,"geoNamesId":2660207,"wikipediaId":123048,"esosediId":7487859,"iso3166":"CH-JU"}},"1697465":{"level":6,"parents":[{"id":1697347,"delta":-2},{"id":51701,"delta":-4}],"name":"Делемонт Дистрикт","wikipedia":"en:Delémont_District","index":1,"square":647154839.9081616,"property":{"openStreetMapId":1697465,"geoNamesId":6458744,"wikipediaId":510908,"esosediId":1000271853,"iso3166":""}},"1697529":{"level":6,"parents":[{"id":1697347,"delta":-2},{"id":51701,"delta":-4}],"name":"Поррентруй Дистрикт","wikipedia":"en:Porrentruy_District","index":2,"square":722426863.8652384,"property":{"openStreetMapId":1697529,"geoNamesId":6458776,"wikipediaId":510909,"esosediId":1000263275,"iso3166":""}},"1697530":{"level":6,"parents":[{"id":1697347,"delta":-2},{"id":51701,"delta":-4}],"name":"Франчес-Монтагнес Дистрикт","wikipedia":"en:Franches-Montagnes_District","index":3,"square":420338843.4164863,"property":{"openStreetMapId":1697530,"geoNamesId":6458790,"wikipediaId":510910,"esosediId":1000264052,"iso3166":""}}}