{"61549":{"level":4,"parents":[{"id":1428125,"delta":-2}],"name":"Québec","wikipedia":"en:Quebec","index":3,"square":16672750421.792274,"property":{"openStreetMapId":61549,"geoNamesId":6115047,"wikipediaId":541094,"esosediId":1000258899,"iso3166":"CA-QC"}},"68841":{"level":4,"parents":[{"id":1428125,"delta":-2}],"name":"Ontario","wikipedia":"en:Ontario","index":5,"square":498382433.6400419,"property":{"openStreetMapId":68841,"geoNamesId":6093943,"wikipediaId":541876,"esosediId":1000258897,"iso3166":"CA-ON"}},"68942":{"level":4,"parents":[{"id":1428125,"delta":-2}],"name":"New Brunswick","wikipedia":"en:New_Brunswick","index":12,"square":153872775274.09665,"property":{"openStreetMapId":68942,"geoNamesId":6087430,"wikipediaId":541821,"esosediId":1000258892,"iso3166":"CA-NB"}},"390558":{"level":4,"parents":[{"id":1428125,"delta":-2}],"name":"Nova Scotia","wikipedia":"en:Nova_Scotia","index":11,"square":631079493.7051908,"property":{"openStreetMapId":390558,"geoNamesId":6091530,"wikipediaId":541788,"esosediId":1000258894,"iso3166":"CA-NS"}},"390840":{"level":4,"parents":[{"id":1428125,"delta":-2}],"name":"Nunavut","wikipedia":"en:Nunavut","index":1,"square":21427769752386.457,"property":{"openStreetMapId":390840,"geoNamesId":6091732,"wikipediaId":541809,"esosediId":1000258896,"iso3166":"CA-NU"}},"390841":{"level":4,"parents":[{"id":1428125,"delta":-2}],"name":"Manitoba","wikipedia":"en:Manitoba","index":8,"square":177396027.85162506,"property":{"openStreetMapId":390841,"geoNamesId":6065171,"wikipediaId":541516,"esosediId":1000258891,"iso3166":"CA-MB"}},"390867":{"level":4,"parents":[{"id":1428125,"delta":-2}],"name":"British Columbia","wikipedia":"en:British_Columbia","index":4,"square":2859751197476.923,"property":{"openStreetMapId":390867,"geoNamesId":5909050,"wikipediaId":540313,"esosediId":1000258890,"iso3166":"CA-BC"}},"391115":{"level":4,"parents":[{"id":1428125,"delta":-2}],"name":"Prince Edward Island","wikipedia":"en:Prince_Edward_Island","index":13,"square":17271646325.06274,"property":{"openStreetMapId":391115,"geoNamesId":6113358,"wikipediaId":541901,"esosediId":1000258898,"iso3166":"CA-PE"}},"391178":{"level":4,"parents":[{"id":1428125,"delta":-2}],"name":"Saskatchewan","wikipedia":"en:Saskatchewan","index":10,"square":1935476594578.9648,"property":{"openStreetMapId":391178,"geoNamesId":6141242,"wikipediaId":542302,"esosediId":1000258900,"iso3166":"CA-SK"}},"391186":{"level":4,"parents":[{"id":1428125,"delta":-2}],"name":"Alberta","wikipedia":"en:Alberta","index":9,"square":2040002688300.5376,"property":{"openStreetMapId":391186,"geoNamesId":5883102,"wikipediaId":539981,"esosediId":1000258889,"iso3166":"CA-AB"}},"391196":{"level":4,"parents":[{"id":1428125,"delta":-2}],"name":"Newfoundland and Labrador","wikipedia":"en:Newfoundland_and_Labrador","index":6,"square":54941030805.71672,"property":{"openStreetMapId":391196,"geoNamesId":6354959,"wikipediaId":338260,"esosediId":1000258893,"iso3166":"CA-NL"}},"391220":{"level":4,"parents":[{"id":1428125,"delta":-2}],"name":"Northwest Territories","wikipedia":"en:Northwest_Territories","index":2,"square":8269978891293.1045,"property":{"openStreetMapId":391220,"geoNamesId":6091069,"wikipediaId":542384,"esosediId":1000258895,"iso3166":"CA-NT"}},"391455":{"level":4,"parents":[{"id":1428125,"delta":-2}],"name":"Yukon","wikipedia":"en:Yukon","index":7,"square":2463098219214.36,"property":{"openStreetMapId":391455,"geoNamesId":6185811,"wikipediaId":544399,"esosediId":1000258901,"iso3166":"CA-YT"}},"1428125":{"level":2,"parents":[],"name":"Canada","wikipedia":"ru:Канада","index":0,"square":51259866071602.81,"property":{"openStreetMapId":1428125,"geoNamesId":6251999,"wikipediaId":331369,"esosediId":1000258477,"iso3166":"CA","worldRegion":["Americas","Northern America"]}},"1797927":{"level":3,"parents":[{"id":1428125,"delta":-1}],"name":"Goldstream 13","wikipedia":false,"index":15,"square":1015.11202750355,"property":{"openStreetMapId":1797927,"geoNamesId":0,"wikipediaId":0,"esosediId":1000260911,"iso3166":""}},"2840306":{"level":8,"parents":[{"id":1428125,"delta":-6}],"name":"Ramea","wikipedia":false,"index":14,"square":1549129.0170517266,"property":{"openStreetMapId":2840306,"geoNamesId":6116233,"wikipediaId":327192,"esosediId":1000297914,"iso3166":""}}}