{"223537":{"level":4,"parents":[{"id":2094154,"delta":-1},{"id":174737,"delta":-2}],"name":"Tunceli Province","wikipedia":"en:Tunceli_Province","index":0,"square":12466162952.130104,"property":{"openStreetMapId":223537,"geoNamesId":298845,"wikipediaId":542709,"esosediId":1000260641,"iso3166":"TR-62"}},"1829324":{"level":6,"parents":[{"id":223537,"delta":-2},{"id":2094154,"delta":-3},{"id":174737,"delta":-4}],"name":"Hozat","wikipedia":"ru:Хозат","index":6,"square":986086175.3781185,"property":{"openStreetMapId":1829324,"geoNamesId":311869,"wikipediaId":17550,"esosediId":1000272972,"iso3166":""}},"1829325":{"level":6,"parents":[{"id":223537,"delta":-2},{"id":2094154,"delta":-3},{"id":174737,"delta":-4}],"name":"Mazkirt","wikipedia":false,"index":7,"square":1003028615.4843159,"property":{"openStreetMapId":1829325,"geoNamesId":304738,"wikipediaId":0,"esosediId":1000273744,"iso3166":""}},"1829326":{"level":6,"parents":[{"id":223537,"delta":-2},{"id":2094154,"delta":-3},{"id":174737,"delta":-4}],"name":"Nazımiye","wikipedia":"ru:Назымие","index":8,"square":914654634.7028477,"property":{"openStreetMapId":1829326,"geoNamesId":303872,"wikipediaId":552325,"esosediId":1000274515,"iso3166":""}},"1829327":{"level":6,"parents":[{"id":223537,"delta":-2},{"id":2094154,"delta":-3},{"id":174737,"delta":-4}],"name":"Ovacık, Dersim","wikipedia":"ru:Оваджык","index":1,"square":2513615997.555792,"property":{"openStreetMapId":1829327,"geoNamesId":303107,"wikipediaId":17199,"esosediId":1000262852,"iso3166":""}},"1829328":{"level":6,"parents":[{"id":223537,"delta":-2},{"id":2094154,"delta":-3},{"id":174737,"delta":-4}],"name":"Pertek","wikipedia":"ru:Пертек","index":4,"square":1424305431.5014439,"property":{"openStreetMapId":1829328,"geoNamesId":302724,"wikipediaId":17178,"esosediId":1000263624,"iso3166":""}},"1829329":{"level":6,"parents":[{"id":223537,"delta":-2},{"id":2094154,"delta":-3},{"id":174737,"delta":-4}],"name":"Pülümür","wikipedia":"ru:Пюлюмюр","index":2,"square":2282101172.2366314,"property":{"openStreetMapId":1829329,"geoNamesId":302469,"wikipediaId":17165,"esosediId":1000264406,"iso3166":""}},"1829330":{"level":6,"parents":[{"id":223537,"delta":-2},{"id":2094154,"delta":-3},{"id":174737,"delta":-4}],"name":"Tunceli merkez","wikipedia":false,"index":3,"square":1856801656.8777647,"property":{"openStreetMapId":1829330,"geoNamesId":0,"wikipediaId":0,"esosediId":1000265185,"iso3166":""}},"1829331":{"level":6,"parents":[{"id":223537,"delta":-2},{"id":2094154,"delta":-3},{"id":174737,"delta":-4}],"name":"Çemişgezek","wikipedia":"ru:Чемишгезек","index":5,"square":1477958957.92285,"property":{"openStreetMapId":1829331,"geoNamesId":318849,"wikipediaId":17899,"esosediId":1000265946,"iso3166":""}}}