{"174742":{"level":4,"parents":[{"id":2094154,"delta":-1},{"id":174737,"delta":-2}],"name":"Hakkâri Province","wikipedia":"en:Hakkâri_Province","index":0,"square":11180131002.469788,"property":{"openStreetMapId":174742,"geoNamesId":312888,"wikipediaId":542862,"esosediId":1000260610,"iso3166":"TR-30"}},"1381572":{"level":6,"parents":[{"id":174742,"delta":-2},{"id":2094154,"delta":-3},{"id":174737,"delta":-4}],"name":"Hakkari merkez","wikipedia":false,"index":2,"square":3282626855.0813427,"property":{"openStreetMapId":1381572,"geoNamesId":0,"wikipediaId":0,"esosediId":1000265197,"iso3166":""}},"1381573":{"level":6,"parents":[{"id":174742,"delta":-2},{"id":2094154,"delta":-3},{"id":174737,"delta":-4}],"name":"Yüksekova","wikipedia":"ru:Юксекова","index":1,"square":3859686690.787659,"property":{"openStreetMapId":1381573,"geoNamesId":7733232,"wikipediaId":418357,"esosediId":1000265962,"iso3166":""}},"1381574":{"level":6,"parents":[{"id":174742,"delta":-2},{"id":2094154,"delta":-3},{"id":174737,"delta":-4}],"name":"Şemdinli","wikipedia":"ru:Шемдинли","index":3,"square":2604351678.0337744,"property":{"openStreetMapId":1381574,"geoNamesId":301209,"wikipediaId":17112,"esosediId":1000266721,"iso3166":""}},"1776630":{"level":6,"parents":[{"id":174742,"delta":-2},{"id":2094154,"delta":-3},{"id":174737,"delta":-4}],"name":"Çukurca","wikipedia":"ru:Чукурджа","index":4,"square":1402229674.1841383,"property":{"openStreetMapId":1776630,"geoNamesId":317953,"wikipediaId":17860,"esosediId":1000263959,"iso3166":""}}}